{
	"archive" : {},
	"artifacts" : 
	[
		{
			"path" : "lib/graph/libgraph.a"
		}
	],
	"backtrace" : 1,
	"backtraceGraph" : 
	{
		"commands" : 
		[
			"add_library"
		],
		"files" : 
		[
			"lib/graph/CMakeLists.txt"
		],
		"nodes" : 
		[
			{
				"file" : 0
			},
			{
				"command" : 0,
				"file" : 0,
				"line" : 3,
				"parent" : 0
			}
		]
	},
	"id" : "graph::@05e0b547915bc312053c",
	"name" : "graph",
	"nameOnDisk" : "libgraph.a",
	"paths" : 
	{
		"build" : "lib/graph",
		"source" : "lib/graph"
	},
	"sourceGroups" : 
	[
		{
			"name" : "Header Files",
			"sourceIndexes" : 
			[
				0,
				1,
				2,
				3
			]
		}
	],
	"sources" : 
	[
		{
			"backtrace" : 1,
			"path" : "lib/graph/city.h",
			"sourceGroupIndex" : 0
		},
		{
			"backtrace" : 1,
			"path" : "lib/graph/edge.h",
			"sourceGroupIndex" : 0
		},
		{
			"backtrace" : 1,
			"path" : "lib/graph/graph.h",
			"sourceGroupIndex" : 0
		},
		{
			"backtrace" : 1,
			"path" : "lib/graph/node.h",
			"sourceGroupIndex" : 0
		}
	],
	"type" : "STATIC_LIBRARY"
}
